pytranscripts/__init__.py
pytranscripts/core.py
pytranscripts/exports.py
pytranscripts/streamlit_app.py
pytranscripts/training.py
pytranscripts/utils.py
pytranscripts-1.5.1.dist-info/LICENSE
pytranscripts-1.5.1.dist-info/METADATA
pytranscripts-1.5.1.dist-info/WHEEL
pytranscripts-1.5.1.dist-info/top_level.txt
pytranscripts-1.5.1.dist-info/RECORD
